[
	{ "s": "В", "p": [10, 13, 11, 8, 3, 6, 12, 9, 4] },
	{ "s": "ВАМ", "p": [4] },
	{ "s": "ВАМИ", "p": [10] },
	{ "s": "ВАС", "p": [9] },
	{ "s": "ВАШЕГО", "p": [3] },
	{ "s": "ВАШЕЙ", "p": [4] },
	{ "s": "ВАШИМ", "p": [10] },
	{ "s": "ВВЕРХ", "p": [13] },
	{ "s": "ВЕЙ", "p": [8] },
	{ "s": "ВЕР", "p": [11] },
	{ "s": "ВЕРСИИ", "p": [11, 10, 8, 4] },
	{ "s": "ВЕРСИЮ", "p": [11, 7] },
	{ "s": "ВЕРСИЯ", "p": [11, 8] },
	{ "s": "ВЕРСИЯМИ", "p": [11] },
	{ "s": "ВЗАИМОДЕЙСТВУЕТ", "p": [10] },
	{ "s": "ВКЛАДЧИКОВ", "p": [8] },
	{ "s": "ВКЛЮЧАЕТ", "p": [10, 11] },
	{ "s": "ВКЛЮЧАЯ", "p": [8, 10, 6] },
	{ "s": "ВКЛЮЧЕНА", "p": [11] },
	{ "s": "ВКЛЮЧЕНИЯ", "p": [3] },
	{ "s": "ВКЛЮЧЕННЫЕ", "p": [8] },
	{ "s": "ВКЛЮЧЕННЫМИ", "p": [10] },
	{ "s": "ВЛАДЕЛЬЦА", "p": [8] },
	{ "s": "ВЛЕВО", "p": [13] },
	{ "s": "ВЛОЖЕННОСТИ", "p": [13] },
	{ "s": "ВНЕ", "p": [10] },
	{ "s": "ВНЕШНИЕ", "p": [13] },
	{ "s": "ВНИЗ", "p": [13] },
	{ "s": "ВНИМАТЕЛЬНО", "p": [10] },
	{ "s": "ВНОСИТЬ", "p": [10] },
	{ "s": "ВНОСЯТСЯ", "p": [10] },
	{ "s": "ВО", "p": [8] },
	{ "s": "ВОДЯНОЙ", "p": [11] },
	{ "s": "ВОДЯНЫЕ", "p": [11] },
	{ "s": "ВОЗМЕЩЕНИЕ", "p": [10] },
	{ "s": "ВОЗМОЖНО", "p": [12] },
	{ "s": "ВОЗМОЖНОЙ", "p": [11] },
	{ "s": "ВОЗМОЖНОСТИ", "p": [11, 8] },
	{ "s": "ВОЗМОЖНОСТЬ", "p": [10, 3] },
	{ "s": "ВОЗМОЖНОСТЯМИ", "p": [11, 4] },
	{ "s": "ВОЗМОЖНЫХ", "p": [10] },
	{ "s": "ВОЗНАГРАЖДЕНИЯ", "p": [10] },
	{ "s": "ВОЗНИКАЮЩИЕ", "p": [10] },
	{ "s": "ВОЗНИКАЮЩИХ", "p": [8] },
	{ "s": "ВОЗНИКЛИ", "p": [8] },
	{ "s": "ВОЗНИКНОВЕНИЯ", "p": [10] },
	{ "s": "ВОЗНИКШИЕ", "p": [10, 8] },
	{ "s": "ВОПРОСЫ", "p": [9] },
	{ "s": "ВОСПОЛЬЗОВАТЬСЯ", "p": [11] },
	{ "s": "ВОСПРОИЗВОДИТЬ", "p": [8] },
	{ "s": "ВПРАВЕ", "p": [10] },
	{ "s": "ВПРАВО", "p": [13] },
	{ "s": "ВРЕМЕНИ", "p": [11] },
	{ "s": "ВРЕМЯ", "p": [10] },
	{ "s": "ВСЕ", "p": [11, 8, 13, 10] },
	{ "s": "ВСЕМ", "p": [4] },
	{ "s": "ВСЕМИ", "p": [11] },
	{ "s": "ВСЕХ", "p": [8, 13, 10] },
	{ "s": "ВСПЛЫВАЮЩИЕ", "p": [11] },
	{ "s": "ВСТАВИТЬ", "p": [13] },
	{ "s": "ВСТРАИВАЙТЕ", "p": [3] },
	{ "s": "ВСТРОЕННЫМ", "p": [3] },
	{ "s": "ВХОДЯЩИХ", "p": [10] },
	{ "s": "ВЫ", "p": [10, 11, 13, 7, 6, 4, 3] },
	{ "s": "ВЫБОР", "p": [6] },
	{ "s": "ВЫБРАННЫЙ", "p": [13] },
	{ "s": "ВЫВОД", "p": [11] },
	{ "s": "ВЫВОДА", "p": [3] },
	{ "s": "ВЫГОДУ", "p": [10] },
	{ "s": "ВЫДЕЛЯЮТ", "p": [6] },
	{ "s": "ВЫНОСКАМИ", "p": [3] },
	{ "s": "ВЫПАДАЮЩЕЕ", "p": [13] },
	{ "s": "ВЫПОЛНИТЬ", "p": [12] },
	{ "s": "ВЫРЕЗАТЬ", "p": [13] },
	{ "s": "ВЫСТУПАЮЩИЙ", "p": [10] },
	{ "s": "ВЫХОДА", "p": [11] },
	{ "s": "ВЫШЕУКАЗАННОЕ", "p": [8] },
	{ "s": "ВЫШЕУКАЗАННЫЕ", "p": [8] },
	{ "s": "ВЫШЕУКАЗАННЫХ", "p": [8] },
	{ "s": "ВЫШЕУПОМЯНУТОЕ", "p": [8] }
]