[
	{ "s": "S", "p": [10] },
	{ "s": "SAFEST", "p": [10] },
	{ "s": "SAKE", "p": [10] },
	{ "s": "SALE", "p": [10] },
	{ "s": "SAME", "p": [10] },
	{ "s": "SATISFY", "p": [10] },
	{ "s": "SAYING", "p": [10] },
	{ "s": "SAYS", "p": [10] },
	{ "s": "SCHOOL", "p": [10] },
	{ "s": "SCOPE", "p": [10] },
	{ "s": "SCRIPT", "p": [10] },
	{ "s": "SCRIPTS", "p": [10] },
	{ "s": "SE", "p": [10] },
	{ "s": "SECONDARILY", "p": [10] },
	{ "s": "SECTION", "p": [10] },
	{ "s": "SECTIONS", "p": [10] },
	{ "s": "SEE", "p": [10] },
	{ "s": "SELL", "p": [10] },
	{ "s": "SELLING", "p": [10] },
	{ "s": "SEMICONDUCTOR", "p": [10] },
	{ "s": "SENT", "p": [10] },
	{ "s": "SEPARABLE", "p": [10] },
	{ "s": "SEPARATE", "p": [10] },
	{ "s": "SEPARATELY", "p": [10] },
	{ "s": "SERVER", "p": [10, 7] },
	{ "s": "SERVES", "p": [10] },
	{ "s": "SERVICE", "p": [10] },
	{ "s": "SERVICES", "p": [10] },
	{ "s": "SERVICING", "p": [10] },
	{ "s": "SERVIDOR", "p": [10] },
	{ "s": "SETUP", "p": [12] },
	{ "s": "SETUP.EXE", "p": [12] },
	{ "s": "SHALL", "p": [10] },
	{ "s": "SHARE", "p": [10] },
	{ "s": "SHARED", "p": [10] },
	{ "s": "SHARES", "p": [10] },
	{ "s": "SHEMANAREV", "p": [10] },
	{ "s": "SHORT", "p": [10] },
	{ "s": "SHOULD", "p": [10] },
	{ "s": "SHOW", "p": [10] },
	{ "s": "SIDE", "p": [10] },
	{ "s": "SIERRA", "p": [10] },
	{ "s": "SIGN", "p": [10] },
	{ "s": "SIGNIFICANT", "p": [10] },
	{ "s": "SIMILAR", "p": [10] },
	{ "s": "SIMPLE", "p": [10] },
	{ "s": "SIMULTANEOUSLY", "p": [10] },
	{ "s": "SIMÕES", "p": [10] },
	{ "s": "SINGLE", "p": [10] },
	{ "s": "SMALL", "p": [10] },
	{ "s": "SMARTSCREEN", "p": [10] },
	{ "s": "SO", "p": [10] },
	{ "s": "SOFTWARE", "p": [10] },
	{ "s": "SOLD", "p": [10] },
	{ "s": "SOLE", "p": [10] },
	{ "s": "SOLELY", "p": [10] },
	{ "s": "SOLUTIONS", "p": [10] },
	{ "s": "SOME", "p": [10] },
	{ "s": "SOURCE", "p": [10] },
	{ "s": "SOURCEFORGE", "p": [10] },
	{ "s": "SPAN", "p": [10] },
	{ "s": "SPARE", "p": [10] },
	{ "s": "SPEAK", "p": [10] },
	{ "s": "SPECIAL", "p": [10] },
	{ "s": "SPECIFIC", "p": [10] },
	{ "s": "SPECIFICALLY", "p": [10] },
	{ "s": "SPECIFIED", "p": [10] },
	{ "s": "SPECIFIES", "p": [10] },
	{ "s": "SPECIFY", "p": [10] },
	{ "s": "SPELL", "p": [10] },
	{ "s": "SPIRIT", "p": [10] },
	{ "s": "STAND", "p": [10] },
	{ "s": "STANDALONE", "p": [10] },
	{ "s": "STANDARD", "p": [10] },
	{ "s": "STANDARDS", "p": [10] },
	{ "s": "START", "p": [10] },
	{ "s": "STARTS", "p": [10] },
	{ "s": "STATE", "p": [10] },
	{ "s": "STATED", "p": [10] },
	{ "s": "STATEMENT", "p": [10] },
	{ "s": "STATES", "p": [10] },
	{ "s": "STATING", "p": [10] },
	{ "s": "STATUS", "p": [10] },
	{ "s": "STENBERG", "p": [10] },
	{ "s": "STEPS", "p": [10] },
	{ "s": "STILL", "p": [10] },
	{ "s": "STOPPAGE", "p": [10] },
	{ "s": "STORAGE", "p": [10] },
	{ "s": "STRICT", "p": [10] },
	{ "s": "STRUCTURE", "p": [10] },
	{ "s": "STUDIO", "p": [10] },
	{ "s": "SUBCLASS", "p": [10] },
	{ "s": "SUBDIVIDING", "p": [10] },
	{ "s": "SUBJECT", "p": [10] },
	{ "s": "SUBLICENSE", "p": [10] },
	{ "s": "SUBLICENSES", "p": [10] },
	{ "s": "SUBLICENSING", "p": [10] },
	{ "s": "SUBMISSION", "p": [10] },
	{ "s": "SUBMIT", "p": [10, 9] },
	{ "s": "SUBMITTED", "p": [10] },
	{ "s": "SUBPROGRAMS", "p": [10] },
	{ "s": "SUBROUTINE", "p": [10] },
	{ "s": "SUBSECTION", "p": [10] },
	{ "s": "SUBSEQUENTLY", "p": [10] },
	{ "s": "SUBSTANTIAL", "p": [10] },
	{ "s": "SUBSTANTIALLY", "p": [10] },
	{ "s": "SUBSTITUTE", "p": [10] },
	{ "s": "SUCH", "p": [10] },
	{ "s": "SUE", "p": [10] },
	{ "s": "SUFFICE", "p": [10] },
	{ "s": "SUGGESTIONS", "p": [10] },
	{ "s": "SUITABILITY", "p": [10] },
	{ "s": "SUITABLE", "p": [10] },
	{ "s": "SUPERSEDE", "p": [10] },
	{ "s": "SUPPLEMENT", "p": [10] },
	{ "s": "SUPPLEMENTED", "p": [10] },
	{ "s": "SUPPLIED", "p": [10] },
	{ "s": "SUPPLY", "p": [10] },
	{ "s": "SUPPORT", "p": [10, 9] },
	{ "s": "SUPPORT@DREXPLAIN.COM", "p": [9] },
	{ "s": "SUPPORTED", "p": [10] },
	{ "s": "SUPPORTING", "p": [10] },
	{ "s": "SUPPORTS", "p": [10] },
	{ "s": "SURE", "p": [10] },
	{ "s": "SURRENDER", "p": [10] },
	{ "s": "SURVIVE", "p": [10] },
	{ "s": "SUSTAINED", "p": [10] },
	{ "s": "SYNTAX", "p": [10] },
	{ "s": "SYSTEM", "p": [10] },
	{ "s": "SYSTEMATIC", "p": [10] },
	{ "s": "SYSTEMS", "p": [10] }
]